[
 {
  "charts": [
   {
    "chart_name": "Volunteer Sessions",
    "label": "Volunteer Sessions",
    "parent": "Volunteers",
    "parentfield": "charts",
    "parenttype": "Workspace"
   },
   {
    "chart_name": "Volunteer Activity",
    "label": "Volunteer Activity",
    "parent": "Volunteers",
    "parentfield": "charts",
    "parenttype": "Workspace"
   },
   {
    "chart_name": "Supported Communities",
    "label": "Supported Communities",
    "parent": "Volunteers",
    "parentfield": "charts",
    "parenttype": "Workspace"
   },
   {
    "chart_name": "Registered Volunteers",
    "label": "Volunteer Registrations",
    "parent": "Volunteers",
    "parentfield": "charts",
    "parenttype": "Workspace"
   }
  ],
  "content": "[{\"id\":\"OFVGZHFJ7Z\",\"type\":\"chart\",\"data\":{\"chart_name\":\"Volunteer Registrations\",\"col\":6}},{\"id\":\"bY6EvjGvSr\",\"type\":\"chart\",\"data\":{\"chart_name\":\"Volunteer Sessions\",\"col\":6}},{\"id\":\"F51GuEY0Hr\",\"type\":\"chart\",\"data\":{\"chart_name\":\"Volunteer Activity\",\"col\":6}},{\"id\":\"ysDefu7k0M\",\"type\":\"chart\",\"data\":{\"chart_name\":\"Supported Communities\",\"col\":6}},{\"id\":\"8Pt_GhvNhY\",\"type\":\"number_card\",\"data\":{\"number_card_name\":\"Total Volunteered Days\",\"col\":6}},{\"id\":\"scl2uKqQk2\",\"type\":\"spacer\",\"data\":{\"col\":12}},{\"id\":\"4sShEi4b7Z\",\"type\":\"card\",\"data\":{\"card_name\":\"Volunteer Actions\",\"col\":3}},{\"id\":\"f7w9MoLn2F\",\"type\":\"card\",\"data\":{\"card_name\":\"Volunteers\",\"col\":3}},{\"id\":\"P3tGo32AiT\",\"type\":\"card\",\"data\":{\"card_name\":\"Settings\",\"col\":3}},{\"id\":\"QSQG8ZOxpz\",\"type\":\"card\",\"data\":{\"card_name\":\"Clubs\",\"col\":3}},{\"id\":\"t8nH1ufwjc\",\"type\":\"spacer\",\"data\":{\"col\":12}},{\"id\":\"AFhPo9Xfny\",\"type\":\"card\",\"data\":{\"card_name\":\"Reports\",\"col\":4}}]",
  "custom_blocks": [],
  "docstatus": 0,
  "doctype": "Workspace",
  "for_user": "",
  "hide_custom": 0,
  "icon": "heart",
  "indicator_color": "orange",
  "is_hidden": 0,
  "label": "Volunteers",
  "links": [
   {
    "dependencies": null,
    "description": null,
    "hidden": 0,
    "icon": null,
    "is_query_report": 0,
    "label": "Volunteers",
    "link_count": 2,
    "link_to": null,
    "link_type": "DocType",
    "onboard": 0,
    "only_for": null,
    "parent": "Volunteers",
    "parentfield": "links",
    "parenttype": "Workspace",
    "report_ref_doctype": null,
    "type": "Card Break"
   },
   {
    "dependencies": null,
    "description": null,
    "hidden": 0,
    "icon": null,
    "is_query_report": 0,
    "label": "Volunteer Profile",
    "link_count": 0,
    "link_to": "Volunteer Profile",
    "link_type": "DocType",
    "onboard": 0,
    "only_for": null,
    "parent": "Volunteers",
    "parentfield": "links",
    "parenttype": "Workspace",
    "report_ref_doctype": null,
    "type": "Link"
   },
   {
    "dependencies": null,
    "description": null,
    "hidden": 0,
    "icon": null,
    "is_query_report": 0,
    "label": "Volunteer Positions",
    "link_count": 0,
    "link_to": "Volunteer Position Type",
    "link_type": "DocType",
    "onboard": 0,
    "only_for": null,
    "parent": "Volunteers",
    "parentfield": "links",
    "parenttype": "Workspace",
    "report_ref_doctype": null,
    "type": "Link"
   },
   {
    "dependencies": null,
    "description": null,
    "hidden": 0,
    "icon": null,
    "is_query_report": 0,
    "label": "Clubs",
    "link_count": 3,
    "link_to": null,
    "link_type": "DocType",
    "onboard": 0,
    "only_for": null,
    "parent": "Volunteers",
    "parentfield": "links",
    "parenttype": "Workspace",
    "report_ref_doctype": null,
    "type": "Card Break"
   },
   {
    "dependencies": null,
    "description": null,
    "hidden": 0,
    "icon": null,
    "is_query_report": 0,
    "label": "Club",
    "link_count": 0,
    "link_to": "Club",
    "link_type": "DocType",
    "onboard": 0,
    "only_for": null,
    "parent": "Volunteers",
    "parentfield": "links",
    "parenttype": "Workspace",
    "report_ref_doctype": null,
    "type": "Link"
   },
   {
    "dependencies": null,
    "description": null,
    "hidden": 0,
    "icon": null,
    "is_query_report": 0,
    "label": "Club Type",
    "link_count": 0,
    "link_to": "Club Type",
    "link_type": "DocType",
    "onboard": 0,
    "only_for": null,
    "parent": "Volunteers",
    "parentfield": "links",
    "parenttype": "Workspace",
    "report_ref_doctype": null,
    "type": "Link"
   },
   {
    "dependencies": null,
    "description": null,
    "hidden": 0,
    "icon": null,
    "is_query_report": 0,
    "label": "Activity District",
    "link_count": 0,
    "link_to": "Activity District",
    "link_type": "DocType",
    "onboard": 0,
    "only_for": null,
    "parent": "Volunteers",
    "parentfield": "links",
    "parenttype": "Workspace",
    "report_ref_doctype": null,
    "type": "Link"
   },
   {
    "dependencies": null,
    "description": null,
    "hidden": 0,
    "icon": null,
    "is_query_report": 0,
    "label": "Volunteer Actions",
    "link_count": 2,
    "link_to": null,
    "link_type": "DocType",
    "onboard": 0,
    "only_for": null,
    "parent": "Volunteers",
    "parentfield": "links",
    "parenttype": "Workspace",
    "report_ref_doctype": null,
    "type": "Card Break"
   },
   {
    "dependencies": null,
    "description": null,
    "hidden": 0,
    "icon": null,
    "is_query_report": 0,
    "label": "Volunteer Activity Log",
    "link_count": 0,
    "link_to": "Volunteer Log",
    "link_type": "DocType",
    "onboard": 0,
    "only_for": null,
    "parent": "Volunteers",
    "parentfield": "links",
    "parenttype": "Workspace",
    "report_ref_doctype": null,
    "type": "Link"
   },
   {
    "dependencies": null,
    "description": null,
    "hidden": 0,
    "icon": null,
    "is_query_report": 0,
    "label": "Volunteer Feedback",
    "link_count": 0,
    "link_to": "Volunteer Log",
    "link_type": "DocType",
    "onboard": 0,
    "only_for": null,
    "parent": "Volunteers",
    "parentfield": "links",
    "parenttype": "Workspace",
    "report_ref_doctype": null,
    "type": "Link"
   },
   {
    "dependencies": null,
    "description": null,
    "hidden": 0,
    "icon": null,
    "is_query_report": 0,
    "label": "Reports",
    "link_count": 1,
    "link_to": null,
    "link_type": "DocType",
    "onboard": 0,
    "only_for": null,
    "parent": "Volunteers",
    "parentfield": "links",
    "parenttype": "Workspace",
    "report_ref_doctype": null,
    "type": "Card Break"
   },
   {
    "dependencies": null,
    "description": null,
    "hidden": 0,
    "icon": null,
    "is_query_report": 1,
    "label": "Volunteer Report",
    "link_count": 0,
    "link_to": "Volunteer Report",
    "link_type": "Report",
    "onboard": 0,
    "only_for": null,
    "parent": "Volunteers",
    "parentfield": "links",
    "parenttype": "Workspace",
    "report_ref_doctype": null,
    "type": "Link"
   },
   {
    "dependencies": null,
    "description": null,
    "hidden": 0,
    "icon": null,
    "is_query_report": 0,
    "label": "Settings",
    "link_count": 1,
    "link_to": null,
    "link_type": "DocType",
    "onboard": 0,
    "only_for": null,
    "parent": "Volunteers",
    "parentfield": "links",
    "parenttype": "Workspace",
    "report_ref_doctype": null,
    "type": "Card Break"
   },
   {
    "dependencies": null,
    "description": null,
    "hidden": 0,
    "icon": null,
    "is_query_report": 0,
    "label": "Volunteer Settings",
    "link_count": 0,
    "link_to": "Volunteer Settings",
    "link_type": "DocType",
    "onboard": 0,
    "only_for": null,
    "parent": "Volunteers",
    "parentfield": "links",
    "parenttype": "Workspace",
    "report_ref_doctype": null,
    "type": "Link"
   }
  ],
  "modified": "2025-01-15 12:19:48.232384",
  "module": "Volunteer Management",
  "name": "Volunteers",
  "number_cards": [
   {
    "label": "Total Volunteered Days",
    "number_card_name": "Total Volunteer Days",
    "parent": "Volunteers",
    "parentfield": "number_cards",
    "parenttype": "Workspace"
   }
  ],
  "parent_page": "",
  "public": 1,
  "quick_lists": [],
  "restrict_to_domain": null,
  "roles": [],
  "sequence_id": 19.0,
  "shortcuts": [],
  "title": "Volunteers"
 },
 {
  "charts": [
   {
    "chart_name": "Project Summary",
    "label": "Live Project Overview",
    "parent": "Project Management",
    "parentfield": "charts",
    "parenttype": "Workspace"
   }
  ],
  "content": "[{\"id\":\"VDMms0hapk\",\"type\":\"chart\",\"data\":{\"chart_name\":\"Live Project Overview\",\"col\":12}},{\"id\":\"8yqX1lbNMU\",\"type\":\"number_card\",\"data\":{\"number_card_name\":\"Active Projects\",\"col\":3}},{\"id\":\"V7k2uHkX-s\",\"type\":\"number_card\",\"data\":{\"number_card_name\":\"Ongoing Project Activities\",\"col\":3}},{\"id\":\"esunNxOZ0k\",\"type\":\"number_card\",\"data\":{\"number_card_name\":\"Late Project Activities\",\"col\":3}},{\"id\":\"du9GKAXrPw\",\"type\":\"number_card\",\"data\":{\"number_card_name\":\"Completed Activities\",\"col\":3}},{\"id\":\"nyuMo9byw7\",\"type\":\"header\",\"data\":{\"text\":\"<span class=\\\"h4\\\"><b>Your Shortcuts</b></span>\",\"col\":12}},{\"id\":\"VTizthHc-E\",\"type\":\"shortcut\",\"data\":{\"shortcut_name\":\"Project Board\",\"col\":3}},{\"id\":\"dILbX_r0ve\",\"type\":\"shortcut\",\"data\":{\"shortcut_name\":\"Project Tasks\",\"col\":3}},{\"id\":\"JT8ntrqRiJ\",\"type\":\"shortcut\",\"data\":{\"shortcut_name\":\"Projects\",\"col\":3}},{\"id\":\"jx5aPK9aXN\",\"type\":\"shortcut\",\"data\":{\"shortcut_name\":\"Learn Project Management\",\"col\":3}},{\"id\":\"LcAiEYN0re\",\"type\":\"spacer\",\"data\":{\"col\":12}},{\"id\":\"oGhjvYjfv-\",\"type\":\"header\",\"data\":{\"text\":\"<span class=\\\"h4\\\"><b>Reports &amp; Masters</b></span>\",\"col\":12}},{\"id\":\"TdsgJyG3EI\",\"type\":\"card\",\"data\":{\"card_name\":\"Projects\",\"col\":3}},{\"id\":\"nIc0iyvf1T\",\"type\":\"card\",\"data\":{\"card_name\":\"Time Tracking\",\"col\":3}},{\"id\":\"8G1if4jsQ7\",\"type\":\"card\",\"data\":{\"card_name\":\"Reports\",\"col\":3}},{\"id\":\"RMGp7dmXEZ\",\"type\":\"spacer\",\"data\":{\"col\":12}},{\"id\":\"3AMXWOm27A\",\"type\":\"custom_block\",\"data\":{\"custom_block_name\":\"easter_egg\",\"col\":12}}]",
  "custom_blocks": [
   {
    "custom_block_name": "easter_egg",
    "label": "easter_egg",
    "parent": "Project Management",
    "parentfield": "custom_blocks",
    "parenttype": "Workspace"
   }
  ],
  "docstatus": 0,
  "doctype": "Workspace",
  "for_user": "",
  "hide_custom": 0,
  "icon": "",
  "indicator_color": "darkgrey",
  "is_hidden": 0,
  "label": "Project Management",
  "links": [
   {
    "dependencies": null,
    "description": null,
    "hidden": 0,
    "icon": null,
    "is_query_report": 0,
    "label": "Time Tracking",
    "link_count": 2,
    "link_to": null,
    "link_type": "DocType",
    "onboard": 0,
    "only_for": null,
    "parent": "Project Management",
    "parentfield": "links",
    "parenttype": "Workspace",
    "report_ref_doctype": null,
    "type": "Card Break"
   },
   {
    "dependencies": "",
    "description": null,
    "hidden": 0,
    "icon": null,
    "is_query_report": 0,
    "label": "Activity Type",
    "link_count": 0,
    "link_to": "Activity Type",
    "link_type": "DocType",
    "onboard": 1,
    "only_for": null,
    "parent": "Project Management",
    "parentfield": "links",
    "parenttype": "Workspace",
    "report_ref_doctype": null,
    "type": "Link"
   },
   {
    "dependencies": "Activity Type",
    "description": null,
    "hidden": 0,
    "icon": null,
    "is_query_report": 0,
    "label": "Activity Cost",
    "link_count": 0,
    "link_to": "Activity Cost",
    "link_type": "DocType",
    "onboard": 0,
    "only_for": null,
    "parent": "Project Management",
    "parentfield": "links",
    "parenttype": "Workspace",
    "report_ref_doctype": null,
    "type": "Link"
   },
   {
    "dependencies": null,
    "description": null,
    "hidden": 0,
    "icon": null,
    "is_query_report": 0,
    "label": "Reports",
    "link_count": 1,
    "link_to": null,
    "link_type": "DocType",
    "onboard": 0,
    "only_for": null,
    "parent": "Project Management",
    "parentfield": "links",
    "parenttype": "Workspace",
    "report_ref_doctype": null,
    "type": "Card Break"
   },
   {
    "dependencies": "Task",
    "description": null,
    "hidden": 0,
    "icon": null,
    "is_query_report": 1,
    "label": "Delayed Tasks Summary",
    "link_count": 0,
    "link_to": "Delayed Tasks Summary",
    "link_type": "Report",
    "onboard": 0,
    "only_for": null,
    "parent": "Project Management",
    "parentfield": "links",
    "parenttype": "Workspace",
    "report_ref_doctype": null,
    "type": "Link"
   },
   {
    "dependencies": null,
    "description": null,
    "hidden": 0,
    "icon": null,
    "is_query_report": 0,
    "label": "Projects",
    "link_count": 4,
    "link_to": null,
    "link_type": "DocType",
    "onboard": 0,
    "only_for": null,
    "parent": "Project Management",
    "parentfield": "links",
    "parenttype": "Workspace",
    "report_ref_doctype": null,
    "type": "Card Break"
   },
   {
    "dependencies": "",
    "description": null,
    "hidden": 0,
    "icon": null,
    "is_query_report": 0,
    "label": "Project Template",
    "link_count": 0,
    "link_to": "Project Template",
    "link_type": "DocType",
    "onboard": 0,
    "only_for": null,
    "parent": "Project Management",
    "parentfield": "links",
    "parenttype": "Workspace",
    "report_ref_doctype": null,
    "type": "Link"
   },
   {
    "dependencies": "",
    "description": null,
    "hidden": 0,
    "icon": null,
    "is_query_report": 0,
    "label": "Project Type",
    "link_count": 0,
    "link_to": "Project Type",
    "link_type": "DocType",
    "onboard": 0,
    "only_for": null,
    "parent": "Project Management",
    "parentfield": "links",
    "parenttype": "Workspace",
    "report_ref_doctype": null,
    "type": "Link"
   },
   {
    "dependencies": "Project",
    "description": null,
    "hidden": 0,
    "icon": null,
    "is_query_report": 0,
    "label": "Project Update",
    "link_count": 0,
    "link_to": "Project Update",
    "link_type": "DocType",
    "onboard": 0,
    "only_for": null,
    "parent": "Project Management",
    "parentfield": "links",
    "parenttype": "Workspace",
    "report_ref_doctype": null,
    "type": "Link"
   },
   {
    "dependencies": null,
    "description": null,
    "hidden": 0,
    "icon": null,
    "is_query_report": 0,
    "label": "Projects Settings",
    "link_count": 0,
    "link_to": "Projects Settings",
    "link_type": "DocType",
    "onboard": 0,
    "only_for": null,
    "parent": "Project Management",
    "parentfield": "links",
    "parenttype": "Workspace",
    "report_ref_doctype": null,
    "type": "Link"
   }
  ],
  "modified": "2025-01-15 12:19:47.832544",
  "module": "Malaria Partners",
  "name": "Project Management",
  "number_cards": [
   {
    "label": "Ongoing Project Activities",
    "number_card_name": "Ongoing Project Activities",
    "parent": "Project Management",
    "parentfield": "number_cards",
    "parenttype": "Workspace"
   },
   {
    "label": "Late Project Activities",
    "number_card_name": "Late Project Activities",
    "parent": "Project Management",
    "parentfield": "number_cards",
    "parenttype": "Workspace"
   },
   {
    "label": "Completed Activities",
    "number_card_name": "Completed Activities",
    "parent": "Project Management",
    "parentfield": "number_cards",
    "parenttype": "Workspace"
   },
   {
    "label": "Active Projects",
    "number_card_name": "Running Projects",
    "parent": "Project Management",
    "parentfield": "number_cards",
    "parenttype": "Workspace"
   }
  ],
  "parent_page": "",
  "public": 1,
  "quick_lists": [],
  "restrict_to_domain": "",
  "roles": [
   {
    "parent": "Project Management",
    "parentfield": "roles",
    "parenttype": "Workspace",
    "role": "Projects Manager"
   },
   {
    "parent": "Project Management",
    "parentfield": "roles",
    "parenttype": "Workspace",
    "role": "Projects User"
   },
   {
    "parent": "Project Management",
    "parentfield": "roles",
    "parenttype": "Workspace",
    "role": "First Approver"
   },
   {
    "parent": "Project Management",
    "parentfield": "roles",
    "parenttype": "Workspace",
    "role": "Final Approver"
   },
   {
    "parent": "Project Management",
    "parentfield": "roles",
    "parenttype": "Workspace",
    "role": "Director"
   },
   {
    "parent": "Project Management",
    "parentfield": "roles",
    "parenttype": "Workspace",
    "role": "Board Director"
   },
   {
    "parent": "Project Management",
    "parentfield": "roles",
    "parenttype": "Workspace",
    "role": "Executive Director"
   },
   {
    "parent": "Project Management",
    "parentfield": "roles",
    "parenttype": "Workspace",
    "role": "System Manager"
   }
  ],
  "sequence_id": 18.0,
  "shortcuts": [
   {
    "color": "Grey",
    "doc_view": "List",
    "format": null,
    "icon": null,
    "kanban_board": null,
    "label": "Learn Project Management",
    "link_to": null,
    "parent": "Project Management",
    "parentfield": "shortcuts",
    "parenttype": "Workspace",
    "restrict_to_domain": null,
    "stats_filter": null,
    "type": "URL",
    "url": "https://frappe.school/courses/project-management?utm_source=in_app"
   },
   {
    "color": "Blue",
    "doc_view": "List",
    "format": "{} Assigned",
    "icon": null,
    "kanban_board": null,
    "label": "Project Tasks",
    "link_to": "Task",
    "parent": "Project Management",
    "parentfield": "shortcuts",
    "parenttype": "Workspace",
    "restrict_to_domain": null,
    "stats_filter": "[]",
    "type": "DocType",
    "url": null
   },
   {
    "color": "Blue",
    "doc_view": "Kanban",
    "format": "{} Assigned",
    "icon": null,
    "kanban_board": "Project Board",
    "label": "Project Board",
    "link_to": "Task",
    "parent": "Project Management",
    "parentfield": "shortcuts",
    "parenttype": "Workspace",
    "restrict_to_domain": null,
    "stats_filter": "[]",
    "type": "DocType",
    "url": null
   },
   {
    "color": "Blue",
    "doc_view": "List",
    "format": "{} Open",
    "icon": null,
    "kanban_board": null,
    "label": "Projects",
    "link_to": "Project",
    "parent": "Project Management",
    "parentfield": "shortcuts",
    "parenttype": "Workspace",
    "restrict_to_domain": null,
    "stats_filter": "[[\"Project\",\"status\",\"=\",\"Open\",false]]",
    "type": "DocType",
    "url": null
   }
  ],
  "title": "Project Management"
 },
 {
  "charts": [
   {
    "chart_name": "Transport Log",
    "label": "Transport Activity",
    "parent": "Transport",
    "parentfield": "charts",
    "parenttype": "Workspace"
   },
   {
    "chart_name": "Fuel Consumption",
    "label": "Fuel Consumption",
    "parent": "Transport",
    "parentfield": "charts",
    "parenttype": "Workspace"
   }
  ],
  "content": "[{\"id\":\"s_NV9LVONy\",\"type\":\"chart\",\"data\":{\"chart_name\":\"Transport Activity\",\"col\":6}},{\"id\":\"ggCBVe9II6\",\"type\":\"chart\",\"data\":{\"chart_name\":\"Fuel Consumption\",\"col\":6}},{\"id\":\"VinrYK2p3K\",\"type\":\"spacer\",\"data\":{\"col\":12}},{\"id\":\"wtKKo5Ym7g\",\"type\":\"shortcut\",\"data\":{\"shortcut_name\":\"New Driver Log\",\"col\":3}},{\"id\":\"aHsbGC5NHZ\",\"type\":\"spacer\",\"data\":{\"col\":12}},{\"id\":\"wVah1bDwo4\",\"type\":\"card\",\"data\":{\"card_name\":\"Records\",\"col\":6}},{\"id\":\"SIMEzqWTEu\",\"type\":\"card\",\"data\":{\"card_name\":\"Settings\",\"col\":6}}]",
  "custom_blocks": [],
  "docstatus": 0,
  "doctype": "Workspace",
  "for_user": "",
  "hide_custom": 1,
  "icon": "change",
  "indicator_color": "green",
  "is_hidden": 0,
  "label": "Transport",
  "links": [
   {
    "dependencies": null,
    "description": null,
    "hidden": 0,
    "icon": null,
    "is_query_report": 0,
    "label": "Settings",
    "link_count": 1,
    "link_to": null,
    "link_type": "DocType",
    "onboard": 0,
    "only_for": null,
    "parent": "Transport",
    "parentfield": "links",
    "parenttype": "Workspace",
    "report_ref_doctype": null,
    "type": "Card Break"
   },
   {
    "dependencies": null,
    "description": null,
    "hidden": 0,
    "icon": null,
    "is_query_report": 0,
    "label": "Fleet Settings",
    "link_count": 0,
    "link_to": "Fleet Settings",
    "link_type": "DocType",
    "onboard": 0,
    "only_for": null,
    "parent": "Transport",
    "parentfield": "links",
    "parenttype": "Workspace",
    "report_ref_doctype": null,
    "type": "Link"
   },
   {
    "dependencies": null,
    "description": null,
    "hidden": 0,
    "icon": null,
    "is_query_report": 0,
    "label": "Records",
    "link_count": 3,
    "link_to": null,
    "link_type": "DocType",
    "onboard": 0,
    "only_for": null,
    "parent": "Transport",
    "parentfield": "links",
    "parenttype": "Workspace",
    "report_ref_doctype": null,
    "type": "Card Break"
   },
   {
    "dependencies": null,
    "description": null,
    "hidden": 0,
    "icon": null,
    "is_query_report": 0,
    "label": "Driver Log",
    "link_count": 0,
    "link_to": "Driver Log",
    "link_type": "DocType",
    "onboard": 0,
    "only_for": null,
    "parent": "Transport",
    "parentfield": "links",
    "parenttype": "Workspace",
    "report_ref_doctype": null,
    "type": "Link"
   },
   {
    "dependencies": null,
    "description": null,
    "hidden": 0,
    "icon": null,
    "is_query_report": 0,
    "label": "Vehicle",
    "link_count": 0,
    "link_to": "Vehicle",
    "link_type": "DocType",
    "onboard": 0,
    "only_for": null,
    "parent": "Transport",
    "parentfield": "links",
    "parenttype": "Workspace",
    "report_ref_doctype": null,
    "type": "Link"
   },
   {
    "dependencies": null,
    "description": null,
    "hidden": 0,
    "icon": null,
    "is_query_report": 1,
    "label": "Vehicle Usage Report",
    "link_count": 0,
    "link_to": "Vehicle Usage Report",
    "link_type": "Report",
    "onboard": 0,
    "only_for": null,
    "parent": "Transport",
    "parentfield": "links",
    "parenttype": "Workspace",
    "report_ref_doctype": null,
    "type": "Link"
   }
  ],
  "modified": "2025-01-16 15:43:23.416221",
  "module": "Malaria Partners",
  "name": "Transport",
  "number_cards": [],
  "parent_page": "",
  "public": 1,
  "quick_lists": [],
  "restrict_to_domain": null,
  "roles": [
   {
    "parent": "Transport",
    "parentfield": "roles",
    "parenttype": "Workspace",
    "role": "Fleet Manager"
   },
   {
    "parent": "Transport",
    "parentfield": "roles",
    "parenttype": "Workspace",
    "role": "Accounts User"
   },
   {
    "parent": "Transport",
    "parentfield": "roles",
    "parenttype": "Workspace",
    "role": "Accounts Manager"
   },
   {
    "parent": "Transport",
    "parentfield": "roles",
    "parenttype": "Workspace",
    "role": "Projects Manager"
   }
  ],
  "sequence_id": 32.0,
  "shortcuts": [
   {
    "color": "Green",
    "doc_view": "New",
    "format": "{} Open",
    "icon": null,
    "kanban_board": null,
    "label": "New Driver Log",
    "link_to": "Driver Log",
    "parent": "Transport",
    "parentfield": "shortcuts",
    "parenttype": "Workspace",
    "restrict_to_domain": null,
    "stats_filter": "[[\"Driver Log\",\"docstatus\",\"=\",\"1\",false]]",
    "type": "DocType",
    "url": null
   }
  ],
  "title": "Transport"
 },
 {
  "charts": [
   {
    "chart_name": "Supported Communities",
    "label": "Volunteer Supported Communities",
    "parent": "Malaria Partners Dashboard",
    "parentfield": "charts",
    "parenttype": "Workspace"
   },
   {
    "chart_name": "Payment Requisition Approvals",
    "label": "Payment Requisition Approvals",
    "parent": "Malaria Partners Dashboard",
    "parentfield": "charts",
    "parenttype": "Workspace"
   }
  ],
  "content": "[{\"id\":\"tjRVtRE27l\",\"type\":\"number_card\",\"data\":{\"number_card_name\":\"Active Projects\",\"col\":3}},{\"id\":\"f_7JXHSvCR\",\"type\":\"number_card\",\"data\":{\"number_card_name\":\"Ongoing Project Activities\",\"col\":3}},{\"id\":\"ruo_JtpnT7\",\"type\":\"number_card\",\"data\":{\"number_card_name\":\"Late Project Activities\",\"col\":3}},{\"id\":\"OtdsYeH73X\",\"type\":\"number_card\",\"data\":{\"number_card_name\":\"Completed Activities\",\"col\":3}},{\"id\":\"_Z9EwuG4uR\",\"type\":\"number_card\",\"data\":{\"number_card_name\":\"TOTAL VOLUNTEERS\",\"col\":6}},{\"id\":\"Fvuo1MFVDE\",\"type\":\"spacer\",\"data\":{\"col\":12}},{\"id\":\"aJX8K8Elxp\",\"type\":\"chart\",\"data\":{\"chart_name\":\"Payment Requisition Approvals\",\"col\":6}},{\"id\":\"ZUiZ4V_0H3\",\"type\":\"chart\",\"data\":{\"chart_name\":\"Volunteer Supported Communities\",\"col\":6}},{\"id\":\"L8ovYr0Uil\",\"type\":\"paragraph\",\"data\":{\"text\":\"Quick Actions\",\"col\":12}},{\"id\":\"wHWe4LHbzs\",\"type\":\"shortcut\",\"data\":{\"shortcut_name\":\"New Payment Requisition\",\"col\":3}},{\"id\":\"EOWQCbvZMt\",\"type\":\"shortcut\",\"data\":{\"shortcut_name\":\"Manage Volunteers\",\"col\":3}},{\"id\":\"lRe7YTnqzR\",\"type\":\"shortcut\",\"data\":{\"shortcut_name\":\"Todo Board\",\"col\":3}},{\"id\":\"fQwdAtfDEn\",\"type\":\"shortcut\",\"data\":{\"shortcut_name\":\"Project Board\",\"col\":3}},{\"id\":\"shDDzkut_t\",\"type\":\"spacer\",\"data\":{\"col\":12}},{\"id\":\"NRzRpU-nUB\",\"type\":\"custom_block\",\"data\":{\"custom_block_name\":\"made in zambia\",\"col\":12}}]",
  "custom_blocks": [
   {
    "custom_block_name": "made in zambia",
    "label": "made in zambia",
    "parent": "Malaria Partners Dashboard",
    "parentfield": "custom_blocks",
    "parenttype": "Workspace"
   }
  ],
  "docstatus": 0,
  "doctype": "Workspace",
  "for_user": "",
  "hide_custom": 0,
  "icon": "non-profit",
  "indicator_color": "",
  "is_hidden": 0,
  "label": "Malaria Partners Dashboard",
  "links": [],
  "modified": "2025-01-15 12:19:41.025038",
  "module": "Malaria Partners",
  "name": "Malaria Partners Dashboard",
  "number_cards": [
   {
    "label": "Active Projects",
    "number_card_name": "Running Projects",
    "parent": "Malaria Partners Dashboard",
    "parentfield": "number_cards",
    "parenttype": "Workspace"
   },
   {
    "label": "Ongoing Project Activities",
    "number_card_name": "Ongoing Project Activities",
    "parent": "Malaria Partners Dashboard",
    "parentfield": "number_cards",
    "parenttype": "Workspace"
   },
   {
    "label": "Completed Activities",
    "number_card_name": "Completed Activities",
    "parent": "Malaria Partners Dashboard",
    "parentfield": "number_cards",
    "parenttype": "Workspace"
   },
   {
    "label": "TOTAL VOLUNTEERS",
    "number_card_name": "Total Volunteers",
    "parent": "Malaria Partners Dashboard",
    "parentfield": "number_cards",
    "parenttype": "Workspace"
   },
   {
    "label": "Late Project Activities",
    "number_card_name": "Late Project Activities",
    "parent": "Malaria Partners Dashboard",
    "parentfield": "number_cards",
    "parenttype": "Workspace"
   }
  ],
  "parent_page": "",
  "public": 1,
  "quick_lists": [],
  "restrict_to_domain": null,
  "roles": [
   {
    "parent": "Malaria Partners Dashboard",
    "parentfield": "roles",
    "parenttype": "Workspace",
    "role": "Employee"
   },
   {
    "parent": "Malaria Partners Dashboard",
    "parentfield": "roles",
    "parenttype": "Workspace",
    "role": "System Manager"
   },
   {
    "parent": "Malaria Partners Dashboard",
    "parentfield": "roles",
    "parenttype": "Workspace",
    "role": "Projects User"
   },
   {
    "parent": "Malaria Partners Dashboard",
    "parentfield": "roles",
    "parenttype": "Workspace",
    "role": "Board Director"
   },
   {
    "parent": "Malaria Partners Dashboard",
    "parentfield": "roles",
    "parenttype": "Workspace",
    "role": "Director"
   },
   {
    "parent": "Malaria Partners Dashboard",
    "parentfield": "roles",
    "parenttype": "Workspace",
    "role": "First Approver"
   },
   {
    "parent": "Malaria Partners Dashboard",
    "parentfield": "roles",
    "parenttype": "Workspace",
    "role": "Final Approver"
   },
   {
    "parent": "Malaria Partners Dashboard",
    "parentfield": "roles",
    "parenttype": "Workspace",
    "role": "Executive Director"
   },
   {
    "parent": "Malaria Partners Dashboard",
    "parentfield": "roles",
    "parenttype": "Workspace",
    "role": "Projects Manager"
   }
  ],
  "sequence_id": 3.0,
  "shortcuts": [
   {
    "color": "Blue",
    "doc_view": "Kanban",
    "format": null,
    "icon": null,
    "kanban_board": "Project Board",
    "label": "Project Board",
    "link_to": "Task",
    "parent": "Malaria Partners Dashboard",
    "parentfield": "shortcuts",
    "parenttype": "Workspace",
    "restrict_to_domain": null,
    "stats_filter": "[]",
    "type": "DocType",
    "url": null
   },
   {
    "color": "Pink",
    "doc_view": "Kanban",
    "format": "{} Open",
    "icon": null,
    "kanban_board": "Todo Board",
    "label": "Todo Board",
    "link_to": "ToDo",
    "parent": "Malaria Partners Dashboard",
    "parentfield": "shortcuts",
    "parenttype": "Workspace",
    "restrict_to_domain": null,
    "stats_filter": "[[\"ToDo\",\"status\",\"=\",\"Open\",false]]",
    "type": "DocType",
    "url": null
   },
   {
    "color": "Grey",
    "doc_view": "List",
    "format": null,
    "icon": null,
    "kanban_board": null,
    "label": "Manage Volunteers",
    "link_to": null,
    "parent": "Malaria Partners Dashboard",
    "parentfield": "shortcuts",
    "parenttype": "Workspace",
    "restrict_to_domain": null,
    "stats_filter": null,
    "type": "URL",
    "url": "/app/volunteers"
   },
   {
    "color": "Yellow",
    "doc_view": "New",
    "format": null,
    "icon": null,
    "kanban_board": null,
    "label": "New Payment Requisition",
    "link_to": "Payment Requisition",
    "parent": "Malaria Partners Dashboard",
    "parentfield": "shortcuts",
    "parenttype": "Workspace",
    "restrict_to_domain": null,
    "stats_filter": "[[\"Payment Requisition\",\"workflow_state\",\"not in\",[\"cancelled\",\"rejected\"],false]]",
    "type": "DocType",
    "url": null
   }
  ],
  "title": "Malaria Partners Dashboard"
 }
]